{"Title": "Was the Brexit referendum legitimate, and would a second one be so?", "Year": 2019, "Source": "Eur. Polit. Sci.", "Volume": "18", "Issue": 1, "Art.No": null, "PageStart": 126, "PageEnd": 133, "CitedBy": 7, "DOI": "10.1057/s41304-018-0155-x", "Link": "https://www.scopus.com/inward/record.uri?partnerID=HzOxMe3b&scp=85045239119&origin=inward", "Abstract": "\u00a9 2018, European Consortium for Political Research.This article suggests that common arguments questioning the legitimacy of the first Brexit referendum prove flawed, as do certain others supporting the legitimacy of a second referendum. A different case for a second referendum is offered that would have added to the legitimacy of the first, but the opportunity for which has now passed. Nevertheless, it might be legitimate to overturn the first referendum through a normal parliamentary process should there be a significant level of Bremorse among the public, or a general election supporting a change of policy.", "AuthorKeywords": ["Brexit", "Constitutionalism", "Democracy", "Legitimacy", "Referenda"], "IndexKeywords": null, "DocumentType": "Journal", "PublicationStage": null, "OpenAccess": 2, "EID": "2-s2.0-85045239119", "SubjectAreas": [["Political Science and International Relations", "SOCI", "3320"]], "AuthorData": {"35277057700": {"Name": "Bellamy R.", "AuthorID": "35277057700", "AffiliationID": "60022148", "AffiliationName": "Department of Political Science, UCL"}}}