{"Title": "KiDS+2dFLenS+GAMA: Testing the cosmological model with the EG statistic", "Year": 2018, "Source": "Mon. Not. R. Astron. Soc.", "Volume": "479", "Issue": 3, "Art.No": null, "PageStart": 3422, "PageEnd": 3437, "CitedBy": 19, "DOI": "10.1093/mnras/sty1624", "Link": "https://www.scopus.com/inward/record.uri?partnerID=HzOxMe3b&scp=85051464912&origin=inward", "Abstract": "\u00a9 2018 The Author(s). Published by Oxford University Press on behalf of the Royal Astronomical Society.We present a new measurement of EG, which combines measurements of weak gravitational lensing, galaxy clustering, and redshift-space distortions. This statistic was proposed as a consistency test of General Relativity (GR) that is insensitive to linear, deterministic galaxy bias, and the matter clustering amplitude. We combine deep imaging data from KiDS with overlapping spectroscopy from 2dFLenS, BOSS DR12, and GAMA and find EG(z = 0.267) = 0.43 \u00b1 0.13 (GAMA), EG(z = 0.305) = 0.27 \u00b1 0.08 (LOWZ+2dFLOZ), and EG(z = 0.554) = 0.26 \u00b1 0.07 (CMASS+2dFHIZ). We demonstrate that the existing tension in the value of thematter density parameter hinders the robustness of this statistic as solely a test of GR. We find that our EG measurements, as well as existing ones in the literature, favour a lower matter density cosmology than the cosmic microwave background. For a flat \u039bCDM Universe, we find \u03a9m(z = 0) = 0.25 \u00b1 0.03. With this paper, we publicly release the 2dFLenS data set at: http://2dflens.swin.edu.au.", "AuthorKeywords": ["Gravitational lensing: weak", "Large-scale structure of universe", "Surveys, cosmology: observations"], "IndexKeywords": null, "DocumentType": "Journal", "PublicationStage": null, "OpenAccess": 2, "EID": "2-s2.0-85051464912", "SubjectAreas": [["Astronomy and Astrophysics", "PHYS", "3103"], ["Space and Planetary Science", "EART", "1912"]], "AuthorData": {"56992732400": {"Name": "Amon A.", "AuthorID": "56992732400", "AffiliationID": "60110880, 60006858, 60027272", "AffiliationName": "Institute for Astronomy, University of Edinburgh, Royal Observatory"}, "6701712657": {"Name": "Heymans C.", "AuthorID": "6701712657", "AffiliationID": "60110880, 60006858, 60027272", "AffiliationName": "Institute for Astronomy, University of Edinburgh, Royal Observatory"}, "56673801500": {"Name": "Asgari M.", "AuthorID": "56673801500", "AffiliationID": "60110880, 60006858, 60027272", "AffiliationName": "Institute for Astronomy, University of Edinburgh, Royal Observatory"}, "44561139800": {"Name": "Harnois-D\u00e9raps J.", "AuthorID": "44561139800", "AffiliationID": "60110880, 60006858, 60027272", "AffiliationName": "Institute for Astronomy, University of Edinburgh, Royal Observatory"}, "7102960950": {"Name": "Blake C.", "AuthorID": "7102960950", "AffiliationID": "60030804", "AffiliationName": "Centre for Astrophysics and Supercomputing, Swinburne University of Technology"}, "7006427244": {"Name": "Glazebrook K.", "AuthorID": "7006427244", "AffiliationID": "60030804", "AffiliationName": "Centre for Astrophysics and Supercomputing, Swinburne University of Technology"}, "54391260000": {"Name": "Leonard C.D.", "AuthorID": "54391260000", "AffiliationID": "60027950", "AffiliationName": "McWilliams Center for Cosmology, Carnegie Mellon University"}, "24767518700": {"Name": "Bilicki M.", "AuthorID": "24767518700", "AffiliationID": "60117150", "AffiliationName": "National Centre for Nuclear Research, Astrophysics Division"}, "7102513091": {"Name": "Hoekstra H.", "AuthorID": "7102513091", "AffiliationID": "60003878, 60019816", "AffiliationName": "Leiden Observatory, Leiden University"}, "7003478641": {"Name": "Kuijken K.", "AuthorID": "7003478641", "AffiliationID": "60003878, 60019816", "AffiliationName": "Leiden Observatory, Leiden University"}, "56511267600": {"Name": "Choi A.", "AuthorID": "56511267600", "AffiliationID": "60003500", "AffiliationName": "Center for Cosmology and AstroParticle Physics, The Ohio State University"}, "6602464203": {"Name": "Erben T.", "AuthorID": "6602464203", "AffiliationID": "60007493", "AffiliationName": "Argelander-Institut f\u00fcr Astronomie"}, "8833942900": {"Name": "Hildebrandt H.", "AuthorID": "8833942900", "AffiliationID": "60007493", "AffiliationName": "Argelander-Institut f\u00fcr Astronomie"}, "23485209600": {"Name": "Joachimi B.", "AuthorID": "23485209600", "AffiliationID": "60022148", "AffiliationName": "Department of Physics and Astronomy, University College London"}, "24399008600": {"Name": "Joudaki S.", "AuthorID": "24399008600", "AffiliationID": "60026851", "AffiliationName": "Department of Physics, University of Oxford"}, "7003444700": {"Name": "Lidman C.", "AuthorID": "7003444700", "AffiliationID": "60105847", "AffiliationName": "Australian Astronomical Observatory"}, "7005956579": {"Name": "Loveday J.", "AuthorID": "7005956579", "AffiliationID": "60017317", "AffiliationName": "Astronomy Centre, University of Sussex"}, "10641350800": {"Name": "Parkinson D.", "AuthorID": "10641350800", "AffiliationID": "60081106", "AffiliationName": "Korea Astronomy and Space Science Institute"}, "6701439004": {"Name": "Valentijn E.A.", "AuthorID": "6701439004", "AffiliationID": "60011173, 60010023", "AffiliationName": "Kapteyn Astronomical Institute, University of Groningen"}, "35186568300": {"Name": "Wolf C.", "AuthorID": "35186568300", "AffiliationID": "60008950", "AffiliationName": "Research School of Astronomy and Astrophysics, Australian National University"}}}