{"Title": "In case you missed it: The Prenatal Diagnosis editors bring you the most significant advances of 2014", "Year": 2015, "Source": "Prenat. Diagn.", "Volume": "35", "Issue": 1, "Art.No": null, "PageStart": 29, "PageEnd": 34, "CitedBy": 3, "DOI": "10.1002/pd.4551", "Link": "https://www.scopus.com/inward/record.uri?partnerID=HzOxMe3b&scp=84921467954&origin=inward", "Abstract": null, "AuthorKeywords": null, "IndexKeywords": ["Education, Medical, Continuing", "Female", "Fetal Diseases", "Fetoscopy", "Humans", "Nuchal Translucency Measurement", "Pregnancy", "Pregnancy Complications", "Prenatal Diagnosis", "Publishing"], "DocumentType": "Journal", "PublicationStage": null, "OpenAccess": 0, "EID": "2-s2.0-84921467954", "SubjectAreas": [["Obstetrics and Gynecology", "MEDI", "2729"], ["Genetics (clinical)", "MEDI", "2716"]], "AuthorData": {"35308825300": {"Name": "Faas B.", "AuthorID": "35308825300", "AffiliationID": "60002573", "AffiliationName": "Department of Human Genetics, Radboud University Medical Centre"}, "57192855823": {"Name": "Ghidini A.", "AuthorID": "57192855823", "AffiliationID": "60022986", "AffiliationName": "Obstetrics and Gynecology, Georgetown University Hospital"}, "14029514100": {"Name": "Van Mieghem T.", "AuthorID": "14029514100", "AffiliationID": "60025063", "AffiliationName": "Academic Department Development and Regeneration, Biomedical Sciences"}, "7006218373": {"Name": "Deprest J.", "AuthorID": "7006218373", "AffiliationID": "60025063", "AffiliationName": "Academic Department Development and Regeneration, Biomedical Sciences"}, "7006741537": {"Name": "Chitty L.", "AuthorID": "7006741537", "AffiliationID": "60012662", "AffiliationName": "UCL Institute of Child Health, Great Ormond Street Hospital for Children and UCLH NHS Foundation Trusts"}, "7102654629": {"Name": "Bianchi D.", "AuthorID": "7102654629", "AffiliationID": "60011387", "AffiliationName": "Floating Hospital for Children"}}}