{"Title": "Differential limit on the extremely-high-energy cosmic neutrino flux in the presence of astrophysical background from nine years of IceCube data", "Year": 2018, "Source": "Phy. Rev. D", "Volume": "98", "Issue": 6, "Art.No": null, "PageStart": null, "PageEnd": null, "CitedBy": 75, "DOI": "10.1103/PhysRevD.98.062003", "Link": "https://www.scopus.com/inward/record.uri?partnerID=HzOxMe3b&scp=85054533638&origin=inward", "Abstract": "\u00a9 2018 American Physical Society.We report a quasidifferential upper limit on the extremely-high-energy (EHE) neutrino flux above 5\u00d7106 GeV based on an analysis of nine years of IceCube data. The astrophysical neutrino flux measured by IceCube extends to PeV energies, and it is a background flux when searching for an independent signal flux at higher energies, such as the cosmogenic neutrino signal. We have developed a new method to place robust limits on the EHE neutrino flux in the presence of an astrophysical background, whose spectrum has yet to be understood with high precision at PeV energies. A distinct event with a deposited energy above 106 GeV was found in the new two-year sample, in addition to the one event previously found in the seven-year EHE neutrino search. These two events represent a neutrino flux that is incompatible with predictions for a cosmogenic neutrino flux and are considered to be an astrophysical background in the current study. The obtained limit is the most stringent to date in the energy range between 5\u00d7106 and 2\u00d71010 GeV. This result constrains neutrino models predicting a three-flavor neutrino flux of E\u03bd2\u03c6\u03bde+\u03bd\u03bc+\u03bd\u03c4\u22432\u00d710-8 GeV/cm2 sec sr at 109 GeV. A significant part of the parameter space for EHE neutrino production scenarios assuming a proton-dominated composition of ultra-high-energy cosmic rays is disfavored independently of uncertain models of the extragalactic background light which previous IceCube constraints partially relied on.", "AuthorKeywords": null, "IndexKeywords": null, "DocumentType": "Journal", "PublicationStage": null, "OpenAccess": 1, "EID": "2-s2.0-85054533638", "SubjectAreas": [["Physics and Astronomy (miscellaneous)", "PHYS", "3101"]], "AuthorData": {"17342030600": {"Name": "Auffenberg J.", "AuthorID": "17342030600", "AffiliationID": "60016653", "AffiliationName": "III. Physikalisches Institut, RWTH Aachen University"}, "57204101753": {"Name": "Backes P.", "AuthorID": "57204101753", "AffiliationID": "60016653", "AffiliationName": "III. Physikalisches Institut, RWTH Aachen University"}, "57195680777": {"Name": "Brenzke M.", "AuthorID": "57195680777", "AffiliationID": "60016653", "AffiliationName": "III. Physikalisches Institut, RWTH Aachen University"}, "57204109417": {"Name": "Ganster E.", "AuthorID": "57204109417", "AffiliationID": "60016653", "AffiliationName": "III. Physikalisches Institut, RWTH Aachen University"}, "56235732500": {"Name": "Haack C.", "AuthorID": "56235732500", "AffiliationID": "60016653", "AffiliationName": "III. Physikalisches Institut, RWTH Aachen University"}, "57204100563": {"Name": "Halve L.", "AuthorID": "57204100563", "AffiliationID": "60016653", "AffiliationName": "III. Physikalisches Institut, RWTH Aachen University"}, "57198522073": {"Name": "Kalaczynski P.", "AuthorID": "57198522073", "AffiliationID": "60016653", "AffiliationName": "III. Physikalisches Institut, RWTH Aachen University"}, "57195671361": {"Name": "Koschinsky J.P.", "AuthorID": "57195671361", "AffiliationID": "60016653", "AffiliationName": "III. Physikalisches Institut, RWTH Aachen University"}, "55791680200": {"Name": "Leuermann M.", "AuthorID": "55791680200", "AffiliationID": "60016653", "AffiliationName": "III. Physikalisches Institut, RWTH Aachen University"}, "55443894500": {"Name": "R\u00e4del L.", "AuthorID": "55443894500", "AffiliationID": "60016653", "AffiliationName": "III. Physikalisches Institut, RWTH Aachen University"}, "35168178800": {"Name": "Reimann R.", "AuthorID": "35168178800", "AffiliationID": "60016653", "AffiliationName": "III. Physikalisches Institut, RWTH Aachen University"}, "56418224800": {"Name": "Rongen M.", "AuthorID": "56418224800", "AffiliationID": "60016653", "AffiliationName": "III. Physikalisches Institut, RWTH Aachen University"}, "57191290697": {"Name": "Schaufel M.", "AuthorID": "57191290697", "AffiliationID": "60016653", "AffiliationName": "III. Physikalisches Institut, RWTH Aachen University"}, "55516429400": {"Name": "Schoenen S.", "AuthorID": "55516429400", "AffiliationID": "60016653", "AffiliationName": "III. Physikalisches Institut, RWTH Aachen University"}, "57110067100": {"Name": "Schumacher L.", "AuthorID": "57110067100", "AffiliationID": "60016653", "AffiliationName": "III. Physikalisches Institut, RWTH Aachen University"}, "57192377914": {"Name": "Stettner J.", "AuthorID": "57192377914", "AffiliationID": "60016653", "AffiliationName": "III. Physikalisches Institut, RWTH Aachen University"}, "35291046300": {"Name": "Wallraff M.", "AuthorID": "35291046300", "AffiliationID": "60016653", "AffiliationName": "III. Physikalisches Institut, RWTH Aachen University"}, "57218362811": {"Name": "Waza A.", "AuthorID": "57218362811", "AffiliationID": "60016653", "AffiliationName": "III. Physikalisches Institut, RWTH Aachen University"}, "55173318600": {"Name": "Wiebusch C.H.", "AuthorID": "55173318600", "AffiliationID": "60016653", "AffiliationName": "III. Physikalisches Institut, RWTH Aachen University"}, "7401963995": {"Name": "Hill G.C.", "AuthorID": "7401963995", "AffiliationID": "60009512", "AffiliationName": "Department of Physics, University of Adelaide"}, "57194795032": {"Name": "Kyriacou A.", "AuthorID": "57194795032", "AffiliationID": "60009512", "AffiliationName": "Department of Physics, University of Adelaide"}, "57213241639": {"Name": "Robertson S.", "AuthorID": "57213241639", "AffiliationID": "60009512", "AffiliationName": "Department of Physics, University of Adelaide"}, "56924473800": {"Name": "Wallace A.", "AuthorID": "56924473800", "AffiliationID": "60009512", "AffiliationName": "Department of Physics, University of Adelaide"}, "26538316300": {"Name": "Whelan B.J.", "AuthorID": "26538316300", "AffiliationID": "60009512", "AffiliationName": "Department of Physics, University of Adelaide"}, "10141246400": {"Name": "Rawlins K.", "AuthorID": "10141246400", "AffiliationID": "60029489", "AffiliationName": "Department of Physics and Astronomy, University of Alaska Anchorage"}, "49863686300": {"Name": "Jones B.J.P.", "AuthorID": "49863686300", "AffiliationID": "60003467", "AffiliationName": "Department of Physics, University of Texas at Arlington"}, "57204112778": {"Name": "Watson T.B.", "AuthorID": "57204112778", "AffiliationID": "60003467", "AffiliationName": "Department of Physics, University of Texas at Arlington"}, "8095854500": {"Name": "Japaridze G.S.", "AuthorID": "8095854500", "AffiliationID": "60012269", "AffiliationName": "CTSPS, Clark-Atlanta University"}, "57194332702": {"Name": "Dave P.", "AuthorID": "57194332702", "AffiliationID": "60019647", "AffiliationName": "School of Physics, Center for Relativistic Astrophysics, Georgia Institute of Technology"}, "35238956600": {"Name": "Taboada I.", "AuthorID": "35238956600", "AffiliationID": "60019647", "AffiliationName": "School of Physics, Center for Relativistic Astrophysics, Georgia Institute of Technology"}, "57194794334": {"Name": "Tung C.F.", "AuthorID": "57194794334", "AffiliationID": "60019647", "AffiliationName": "School of Physics, Center for Relativistic Astrophysics, Georgia Institute of Technology"}, "6701844074": {"Name": "Fazely A.R.", "AuthorID": "6701844074", "AffiliationID": "60005183", "AffiliationName": "Department of Physics, Southern University"}, "25625434600": {"Name": "Ter-Antonyan S.", "AuthorID": "25625434600", "AffiliationID": "60005183", "AffiliationName": "Department of Physics, Southern University"}, "7405293979": {"Name": "Xu X.W.", "AuthorID": "7405293979", "AffiliationID": "60005183", "AffiliationName": "Department of Physics, Southern University"}, "35236144400": {"Name": "Bay R.", "AuthorID": "35236144400", "AffiliationID": "60025038", "AffiliationName": "Department of Physics, University of California"}, "55615864400": {"Name": "Binder G.", "AuthorID": "55615864400", "AffiliationID": "60007174", "AffiliationName": "Lawrence Berkeley National Laboratory"}, "7003857585": {"Name": "Filimonov K.", "AuthorID": "7003857585", "AffiliationID": "60025038", "AffiliationName": "Department of Physics, University of California"}, "35227530600": {"Name": "Klein S.R.", "AuthorID": "35227530600", "AffiliationID": "60007174", "AffiliationName": "Lawrence Berkeley National Laboratory"}, "54420787400": {"Name": "Miarecki S.", "AuthorID": "54420787400", "AffiliationID": "60007174", "AffiliationName": "Lawrence Berkeley National Laboratory"}, "35213665300": {"Name": "Palczewski T.", "AuthorID": "35213665300", "AffiliationID": "60007174", "AffiliationName": "Lawrence Berkeley National Laboratory"}, "55665123200": {"Name": "Price P.B.", "AuthorID": "55665123200", "AffiliationID": "60025038", "AffiliationName": "Department of Physics, University of California"}, "57202439768": {"Name": "Woschnagg K.", "AuthorID": "57202439768", "AffiliationID": "60025038", "AffiliationName": "Department of Physics, University of California"}, "35236636600": {"Name": "Gerhardt L.", "AuthorID": "35236636600", "AffiliationID": "60007174", "AffiliationName": "Lawrence Berkeley National Laboratory"}, "35236560000": {"Name": "Goldschmidt A.", "AuthorID": "35236560000", "AffiliationID": "60007174", "AffiliationName": "Lawrence Berkeley National Laboratory"}, "7003930467": {"Name": "Nygren D.R.", "AuthorID": "7003930467", "AffiliationID": "60007174", "AffiliationName": "Lawrence Berkeley National Laboratory"}, "35238092400": {"Name": "Przybylski G.T.", "AuthorID": "35238092400", "AffiliationID": "60007174", "AffiliationName": "Lawrence Berkeley National Laboratory"}, "35238945000": {"Name": "Stezelberger T.", "AuthorID": "35238945000", "AffiliationID": "60007174", "AffiliationName": "Lawrence Berkeley National Laboratory"}, "6603803657": {"Name": "Stokstad R.G.", "AuthorID": "6603803657", "AffiliationID": "60007174", "AffiliationName": "Lawrence Berkeley National Laboratory"}, "55617708600": {"Name": "De With M.", "AuthorID": "55617708600", "AffiliationID": "60000762", "AffiliationName": "Institut f\u00fcr Physik, Humboldt-Universit\u00e4tzu Berlin"}, "57188641184": {"Name": "Hebecker D.", "AuthorID": "57188641184", "AffiliationID": "60000762", "AffiliationName": "Institut f\u00fcr Physik, Humboldt-Universit\u00e4tzu Berlin"}, "24076563200": {"Name": "Kolanoski H.", "AuthorID": "24076563200", "AffiliationID": "60000762", "AffiliationName": "Institut f\u00fcr Physik, Humboldt-Universit\u00e4tzu Berlin"}, "55127695200": {"Name": "Kowalski M.", "AuthorID": "55127695200", "AffiliationID": "60030635", "AffiliationName": "DESY"}, "55497477600": {"Name": "Becker Tjus J.", "AuthorID": "55497477600", "AffiliationID": "60005322", "AffiliationName": "Fakult\u00e4t f\u00fcr Physik and Astronomie, Ruhr-Universit\u00e4t Bochum"}, "56458195900": {"Name": "Bos F.", "AuthorID": "56458195900", "AffiliationID": "60005322", "AffiliationName": "Fakult\u00e4t f\u00fcr Physik and Astronomie, Ruhr-Universit\u00e4t Bochum"}, "35810105700": {"Name": "Eichmann B.", "AuthorID": "35810105700", "AffiliationID": "60005322", "AffiliationName": "Fakult\u00e4t f\u00fcr Physik and Astronomie, Ruhr-Universit\u00e4t Bochum"}, "56417311700": {"Name": "Kroll M.", "AuthorID": "56417311700", "AffiliationID": "60005322", "AffiliationName": "Fakult\u00e4t f\u00fcr Physik and Astronomie, Ruhr-Universit\u00e4t Bochum"}, "55053498100": {"Name": "Sch\u00f6neberg S.", "AuthorID": "55053498100", "AffiliationID": "60005322", "AffiliationName": "Fakult\u00e4t f\u00fcr Physik and Astronomie, Ruhr-Universit\u00e4t Bochum"}, "57191406043": {"Name": "Tenholt F.", "AuthorID": "57191406043", "AffiliationID": "60005322", "AffiliationName": "Fakult\u00e4t f\u00fcr Physik and Astronomie, Ruhr-Universit\u00e4t Bochum"}, "55434807600": {"Name": "Aguilar J.A.", "AuthorID": "55434807600", "AffiliationID": "60000145", "AffiliationName": "Universit\u00e9 Libre de Bruxelles, Science Faculty"}, "57070390800": {"Name": "Ansseau I.", "AuthorID": "57070390800", "AffiliationID": "60000145", "AffiliationName": "Universit\u00e9 Libre de Bruxelles, Science Faculty"}, "55053498000": {"Name": "Heereman D.", "AuthorID": "55053498000", "AffiliationID": "60000145", "AffiliationName": "Universit\u00e9 Libre de Bruxelles, Science Faculty"}, "57201619755": {"Name": "Iovine N.", "AuthorID": "57201619755", "AffiliationID": "60000145", "AffiliationName": "Universit\u00e9 Libre de Bruxelles, Science Faculty"}, "35277663500": {"Name": "Mari\u015f I.C.", "AuthorID": "35277663500", "AffiliationID": "60000145", "AffiliationName": "Universit\u00e9 Libre de Bruxelles, Science Faculty"}, "35237835400": {"Name": "Meagher K.", "AuthorID": "35237835400", "AffiliationID": "60000145", "AffiliationName": "Universit\u00e9 Libre de Bruxelles, Science Faculty"}, "35290848200": {"Name": "Meures T.", "AuthorID": "35290848200", "AffiliationID": "60000145", "AffiliationName": "Universit\u00e9 Libre de Bruxelles, Science Faculty"}, "21743180800": {"Name": "O'Murchadha A.", "AuthorID": "21743180800", "AffiliationID": "60000145", "AffiliationName": "Universit\u00e9 Libre de Bruxelles, Science Faculty"}, "55792828300": {"Name": "Pinat E.", "AuthorID": "55792828300", "AffiliationID": "60000145", "AffiliationName": "Universit\u00e9 Libre de Bruxelles, Science Faculty"}, "57069777400": {"Name": "Raab C.", "AuthorID": "57069777400", "AffiliationID": "60000145", "AffiliationName": "Universit\u00e9 Libre de Bruxelles, Science Faculty"}, "57204113464": {"Name": "Renzi G.", "AuthorID": "57204113464", "AffiliationID": "60000145", "AffiliationName": "Universit\u00e9 Libre de Bruxelles, Science Faculty"}, "57201618023": {"Name": "Coppin P.", "AuthorID": "57201618023", "AffiliationID": "60026810", "AffiliationName": "Vrije Universiteit Brussel (VUB), Dienst ELEM"}, "57191291464": {"Name": "Correa P.", "AuthorID": "57191291464", "AffiliationID": "60026810", "AffiliationName": "Vrije Universiteit Brussel (VUB), Dienst ELEM"}, "7004516555": {"Name": "De Clercq C.", "AuthorID": "7004516555", "AffiliationID": "60026810", "AffiliationName": "Vrije Universiteit Brussel (VUB), Dienst ELEM"}, "34970841300": {"Name": "De Vries K.D.", "AuthorID": "34970841300", "AffiliationID": "60026810", "AffiliationName": "Vrije Universiteit Brussel (VUB), Dienst ELEM"}, "56712841500": {"Name": "De Wasseige G.", "AuthorID": "56712841500", "AffiliationID": "60026810", "AffiliationName": "Vrije Universiteit Brussel (VUB), Dienst ELEM"}, "35237836800": {"Name": "L\u00fcnemann J.", "AuthorID": "35237836800", "AffiliationID": "60026810", "AffiliationName": "Vrije Universiteit Brussel (VUB), Dienst ELEM"}, "57194147336": {"Name": "Maggi G.", "AuthorID": "57194147336", "AffiliationID": "60026810", "AffiliationName": "Vrije Universiteit Brussel (VUB), Dienst ELEM"}, "24074958900": {"Name": "Toscano S.", "AuthorID": "24074958900", "AffiliationID": "60026810", "AffiliationName": "Vrije Universiteit Brussel (VUB), Dienst ELEM"}, "6701728881": {"Name": "Van Eijndhoven N.", "AuthorID": "6701728881", "AffiliationID": "60026810", "AffiliationName": "Vrije Universiteit Brussel (VUB), Dienst ELEM"}, "36801087900": {"Name": "Arg\u00fcelles C.", "AuthorID": "36801087900", "AffiliationID": "60022195", "AffiliationName": "Department of Physics, Massachusetts Institute of Technology"}, "56939048600": {"Name": "Axani S.", "AuthorID": "56939048600", "AffiliationID": "60022195", "AffiliationName": "Department of Physics, Massachusetts Institute of Technology"}, "57205486435": {"Name": "Collin G.H.", "AuthorID": "57205486435", "AffiliationID": "60022195", "AffiliationName": "Department of Physics, Massachusetts Institute of Technology"}, "55708469700": {"Name": "Conrad J.M.", "AuthorID": "55708469700", "AffiliationID": "60022195", "AffiliationName": "Department of Physics, Massachusetts Institute of Technology"}, "56604109700": {"Name": "Moulai M.", "AuthorID": "56604109700", "AffiliationID": "60022195", "AffiliationName": "Department of Physics, Massachusetts Institute of Technology"}, "25925106700": {"Name": "Ishihara A.", "AuthorID": "25925106700", "AffiliationID": "60002787", "AffiliationName": "Department of Physics, Institute for Global Prominent Research, Chiba University"}, "55262312400": {"Name": "Lu L.", "AuthorID": "55262312400", "AffiliationID": "60002787", "AffiliationName": "Department of Physics, Institute for Global Prominent Research, Chiba University"}, "57204109403": {"Name": "Makino Y.", "AuthorID": "57204109403", "AffiliationID": "60002787", "AffiliationName": "Department of Physics, Institute for Global Prominent Research, Chiba University"}, "7102429761": {"Name": "Mase K.", "AuthorID": "7102429761", "AffiliationID": "60002787", "AffiliationName": "Department of Physics, Institute for Global Prominent Research, Chiba University"}, "57204116542": {"Name": "Nagai R.", "AuthorID": "57204116542", "AffiliationID": "60002787", "AffiliationName": "Department of Physics, Institute for Global Prominent Research, Chiba University"}, "44462069900": {"Name": "St\u00f6\u00dfl A.", "AuthorID": "44462069900", "AffiliationID": "60002787", "AffiliationName": "Department of Physics, Institute for Global Prominent Research, Chiba University"}, "43361917500": {"Name": "Yoshida S.", "AuthorID": "43361917500", "AffiliationID": "60002787", "AffiliationName": "Department of Physics, Institute for Global Prominent Research, Chiba University"}, "54796449100": {"Name": "Aartsen M.G.", "AuthorID": "54796449100", "AffiliationID": "60020585", "AffiliationName": "Department of Physics and Astronomy, University of Canterbury"}, "7404784354": {"Name": "Adams J.", "AuthorID": "7404784354", "AffiliationID": "60020585", "AffiliationName": "Department of Physics and Astronomy, University of Canterbury"}, "57195318760": {"Name": "Bagherpour H.", "AuthorID": "57195318760", "AffiliationID": "60020585", "AffiliationName": "Department of Physics and Astronomy, University of Canterbury"}, "35236204300": {"Name": "Berley D.", "AuthorID": "35236204300", "AffiliationID": "60020304", "AffiliationName": "Department of Physics, University of Maryland"}, "35236361600": {"Name": "Blaufuss E.", "AuthorID": "35236361600", "AffiliationID": "60020304", "AffiliationName": "Department of Physics, University of Maryland"}, "56417301800": {"Name": "Cheung E.", "AuthorID": "56417301800", "AffiliationID": "60020304", "AffiliationName": "Department of Physics, University of Maryland"}, "54794971100": {"Name": "Felde J.", "AuthorID": "54794971100", "AffiliationID": "60020304", "AffiliationName": "Department of Physics, University of Maryland"}, "57213428362": {"Name": "Friedman E.", "AuthorID": "57213428362", "AffiliationID": "60020304", "AffiliationName": "Department of Physics, University of Maryland"}, "54419988900": {"Name": "Hellauer R.", "AuthorID": "54419988900", "AffiliationID": "60020304", "AffiliationName": "Department of Physics, University of Maryland"}, "35353250500": {"Name": "Hoffman K.D.", "AuthorID": "35353250500", "AffiliationID": "60020304", "AffiliationName": "Department of Physics, University of Maryland"}, "38661443000": {"Name": "Maunu R.", "AuthorID": "38661443000", "AffiliationID": "60020304", "AffiliationName": "Department of Physics, University of Maryland"}, "35227722300": {"Name": "Olivas A.", "AuthorID": "35227722300", "AffiliationID": "60020304", "AffiliationName": "Department of Physics, University of Maryland"}, "55553573200": {"Name": "Schmidt T.", "AuthorID": "55553573200", "AffiliationID": "60020304", "AffiliationName": "Department of Physics, University of Maryland"}, "57219219537": {"Name": "Song M.", "AuthorID": "57219219537", "AffiliationID": "60020304", "AffiliationName": "Department of Physics, University of Maryland"}, "56822182100": {"Name": "Sullivan G.W.", "AuthorID": "56822182100", "AffiliationID": "60020304", "AffiliationName": "Department of Physics, University of Maryland"}, "7103289198": {"Name": "Beatty J.J.", "AuthorID": "7103289198", "AffiliationID": "60003500", "AffiliationName": "Department of Astronomy, Ohio State University"}, "35238927100": {"Name": "Stamatikos M.", "AuthorID": "35238927100", "AffiliationID": "60003500", "AffiliationName": "Department of Physics, Center for Cosmology and Astro-Particle Physics, Ohio State University"}, "35277612500": {"Name": "Sutherland M.", "AuthorID": "35277612500", "AffiliationID": "60003500", "AffiliationName": "Department of Physics, Center for Cosmology and Astro-Particle Physics, Ohio State University"}, "55788383400": {"Name": "Ahlers M.", "AuthorID": "55788383400", "AffiliationID": "60017041, 60030840", "AffiliationName": "Niels Bohr Institute, University of Copenhagen"}, "56319090800": {"Name": "Bourbeau E.", "AuthorID": "56319090800", "AffiliationID": "60017041, 60030840", "AffiliationName": "Niels Bohr Institute, University of Copenhagen"}, "35227495800": {"Name": "Koskinen D.J.", "AuthorID": "35227495800", "AffiliationID": "60017041, 60030840", "AffiliationName": "Niels Bohr Institute, University of Copenhagen"}, "36767872300": {"Name": "Larson M.J.", "AuthorID": "36767872300", "AffiliationID": "60017041, 60030840", "AffiliationName": "Niels Bohr Institute, University of Copenhagen"}, "56417428800": {"Name": "Medici M.", "AuthorID": "56417428800", "AffiliationID": "60017041, 60030840", "AffiliationName": "Niels Bohr Institute, University of Copenhagen"}, "55792726400": {"Name": "Rameez M.", "AuthorID": "55792726400", "AffiliationID": "60017041, 60030840", "AffiliationName": "Niels Bohr Institute, University of Copenhagen"}, "57129609600": {"Name": "Sarkar S.", "AuthorID": "57129609600", "AffiliationID": "60026851", "AffiliationName": "Department of Physics, University of Oxford"}, "57199330444": {"Name": "Stuttard T.", "AuthorID": "57199330444", "AffiliationID": "60017041, 60030840", "AffiliationName": "Niels Bohr Institute, University of Copenhagen"}, "56715278500": {"Name": "B\u00f6rner M.", "AuthorID": "56715278500", "AffiliationID": "60032991", "AffiliationName": "Department of Physics, TU Dortmund University"}, "57192402217": {"Name": "Hoinka T.", "AuthorID": "57192402217", "AffiliationID": "60032991", "AffiliationName": "Department of Physics, TU Dortmund University"}, "57199326263": {"Name": "H\u00fcnnefeld M.", "AuthorID": "57199326263", "AffiliationID": "60032991", "AffiliationName": "Department of Physics, TU Dortmund University"}, "57188854285": {"Name": "Meier M.", "AuthorID": "57188854285", "AffiliationID": "60032991", "AffiliationName": "Department of Physics, TU Dortmund University"}, "56715161500": {"Name": "Menne T.", "AuthorID": "56715161500", "AffiliationID": "60032991", "AffiliationName": "Department of Physics, TU Dortmund University"}, "35238216800": {"Name": "Pieloth D.", "AuthorID": "35238216800", "AffiliationID": "60032991", "AffiliationName": "Department of Physics, TU Dortmund University"}, "7006626313": {"Name": "Rhode W.", "AuthorID": "7006626313", "AffiliationID": "60032991", "AffiliationName": "Department of Physics, TU Dortmund University"}, "36349508400": {"Name": "Ruhe T.", "AuthorID": "36349508400", "AffiliationID": "60032991", "AffiliationName": "Department of Physics, TU Dortmund University"}, "56715688800": {"Name": "Sandrock A.", "AuthorID": "56715688800", "AffiliationID": "60032991", "AffiliationName": "Department of Physics, TU Dortmund University"}, "57188856061": {"Name": "Schlunder P.", "AuthorID": "57188856061", "AffiliationID": "60032991", "AffiliationName": "Department of Physics, TU Dortmund University"}, "57198516037": {"Name": "Soedingrekso J.", "AuthorID": "57198516037", "AffiliationID": "60032991", "AffiliationName": "Department of Physics, TU Dortmund University"}, "16306460300": {"Name": "De Andr\u00e9 J.P.A.M.", "AuthorID": "16306460300", "AffiliationID": "60031707", "AffiliationName": "Department of Physics and Astronomy, Michigan State University"}, "57202729178": {"Name": "Deyoung T.", "AuthorID": "57202729178", "AffiliationID": "60031707", "AffiliationName": "Department of Physics and Astronomy, Michigan State University"}, "47961121100": {"Name": "Hignight J.", "AuthorID": "47961121100", "AffiliationID": "60031707", "AffiliationName": "Department of Physics and Astronomy, Michigan State University"}, "14058651500": {"Name": "Mahn K.B.M.", "AuthorID": "14058651500", "AffiliationID": "60031707", "AffiliationName": "Department of Physics and Astronomy, Michigan State University"}, "44861446400": {"Name": "Micallef J.", "AuthorID": "44861446400", "AffiliationID": "60031707", "AffiliationName": "Department of Physics and Astronomy, Michigan State University"}, "57070394000": {"Name": "Neer G.", "AuthorID": "57070394000", "AffiliationID": "60031707", "AffiliationName": "Department of Physics and Astronomy, Michigan State University"}, "56650945200": {"Name": "Rysewyk D.", "AuthorID": "56650945200", "AffiliationID": "60031707", "AffiliationName": "Department of Physics and Astronomy, Michigan State University"}, "57195775749": {"Name": "Barron J.P.", "AuthorID": "57195775749", "AffiliationID": "60030835", "AffiliationName": "Department of Physics, University of Alberta"}, "57190861266": {"Name": "Giang W.", "AuthorID": "57190861266", "AffiliationID": "60030835", "AffiliationName": "Department of Physics, University of Alberta"}, "35427036600": {"Name": "Grant D.", "AuthorID": "35427036600", "AffiliationID": "60030835", "AffiliationName": "Department of Physics, University of Alberta"}, "15623072600": {"Name": "Kopper C.", "AuthorID": "15623072600", "AffiliationID": "60030835", "AffiliationName": "Department of Physics, University of Alberta"}, "35227737000": {"Name": "Moore R.W.", "AuthorID": "35227737000", "AffiliationID": "60030835", "AffiliationName": "Department of Physics, University of Alberta"}, "55053539000": {"Name": "Nowicki S.C.", "AuthorID": "55053539000", "AffiliationID": "60030835", "AffiliationName": "Department of Physics, University of Alberta"}, "57190854807": {"Name": "Sanchez Herrera S.E.", "AuthorID": "57190854807", "AffiliationID": "60030835", "AffiliationName": "Department of Physics, University of Alberta"}, "57203677261": {"Name": "Sarkar S.", "AuthorID": "57203677261", "AffiliationID": "60030835", "AffiliationName": "Department of Physics, University of Alberta"}, "57195772877": {"Name": "Wandler F.D.", "AuthorID": "57195772877", "AffiliationID": "60030835", "AffiliationName": "Department of Physics, University of Alberta"}, "7201646497": {"Name": "Weaver C.", "AuthorID": "7201646497", "AffiliationID": "60030835", "AffiliationName": "Department of Physics, University of Alberta"}, "44462204100": {"Name": "Wood T.R.", "AuthorID": "44462204100", "AffiliationID": "60030835", "AffiliationName": "Department of Physics, University of Alberta"}, "57219105986": {"Name": "Woolsey E.", "AuthorID": "57219105986", "AffiliationID": "60030835", "AffiliationName": "Department of Physics, University of Alberta"}, "36740649000": {"Name": "Yanez J.P.", "AuthorID": "36740649000", "AffiliationID": "60030835", "AffiliationName": "Department of Physics, University of Alberta"}, "52363081000": {"Name": "Altmann D.", "AuthorID": "52363081000", "AffiliationID": "60000765", "AffiliationName": "Erlangen Centre for Astroparticle Physics, Friedrich-Alexander-Universit\u00e4t Erlangen-N\u00fcrnberg"}, "7004081043": {"Name": "Anton G.", "AuthorID": "7004081043", "AffiliationID": "60000765", "AffiliationName": "Erlangen Centre for Astroparticle Physics, Friedrich-Alexander-Universit\u00e4t Erlangen-N\u00fcrnberg"}, "36349171300": {"Name": "Gl\u00fcsenkamp T.", "AuthorID": "36349171300", "AffiliationID": "60000765", "AffiliationName": "Erlangen Centre for Astroparticle Physics, Friedrich-Alexander-Universit\u00e4t Erlangen-N\u00fcrnberg"}, "55637158200": {"Name": "Katz U.", "AuthorID": "55637158200", "AffiliationID": "60000765", "AffiliationName": "Erlangen Centre for Astroparticle Physics, Friedrich-Alexander-Universit\u00e4t Erlangen-N\u00fcrnberg"}, "57190863825": {"Name": "Kittler T.", "AuthorID": "57190863825", "AffiliationID": "60000765", "AffiliationName": "Erlangen Centre for Astroparticle Physics, Friedrich-Alexander-Universit\u00e4t Erlangen-N\u00fcrnberg"}, "56085137000": {"Name": "Tselengidou M.", "AuthorID": "56085137000", "AffiliationID": "60000765", "AffiliationName": "Erlangen Centre for Astroparticle Physics, Friedrich-Alexander-Universit\u00e4t Erlangen-N\u00fcrnberg"}, "57200504490": {"Name": "Wrede G.", "AuthorID": "57200504490", "AffiliationID": "60000765", "AffiliationName": "Erlangen Centre for Astroparticle Physics, Friedrich-Alexander-Universit\u00e4t Erlangen-N\u00fcrnberg"}, "25958878200": {"Name": "Al Samarai I.", "AuthorID": "25958878200", "AffiliationID": "60004718", "AffiliationName": "D\u00e9partement de Physique Nucl\u00e9aire et Corpusculaire, Universit\u00e9 de Gen\u00e8ve"}, "56578774700": {"Name": "Barbano A.", "AuthorID": "56578774700", "AffiliationID": "60004718", "AffiliationName": "D\u00e9partement de Physique Nucl\u00e9aire et Corpusculaire, Universit\u00e9 de Gen\u00e8ve"}, "57192377100": {"Name": "Bron S.", "AuthorID": "57192377100", "AffiliationID": "60004718", "AffiliationName": "D\u00e9partement de Physique Nucl\u00e9aire et Corpusculaire, Universit\u00e9 de Gen\u00e8ve"}, "57191750094": {"Name": "Carver T.", "AuthorID": "57191750094", "AffiliationID": "60004718", "AffiliationName": "D\u00e9partement de Physique Nucl\u00e9aire et Corpusculaire, Universit\u00e9 de Gen\u00e8ve"}, "57213569306": {"Name": "Christov A.", "AuthorID": "57213569306", "AffiliationID": "60004718", "AffiliationName": "D\u00e9partement de Physique Nucl\u00e9aire et Corpusculaire, Universit\u00e9 de Gen\u00e8ve"}, "7003826464": {"Name": "Montaruli T.", "AuthorID": "7003826464", "AffiliationID": "60004718", "AffiliationName": "D\u00e9partement de Physique Nucl\u00e9aire et Corpusculaire, Universit\u00e9 de Gen\u00e8ve"}, "55935233000": {"Name": "De Ridder S.", "AuthorID": "55935233000", "AffiliationID": "60033316", "AffiliationName": "Department of Physics and Astronomy, University of Gent"}, "17342701700": {"Name": "Labare M.", "AuthorID": "17342701700", "AffiliationID": "60033316", "AffiliationName": "Department of Physics and Astronomy, University of Gent"}, "6701362856": {"Name": "Ryckbosch D.", "AuthorID": "6701362856", "AffiliationID": "60033316", "AffiliationName": "Department of Physics and Astronomy, University of Gent"}, "56681886800": {"Name": "Van Driessche W.", "AuthorID": "56681886800", "AffiliationID": "60033316", "AffiliationName": "Department of Physics and Astronomy, University of Gent"}, "56662875000": {"Name": "Vanheule S.", "AuthorID": "56662875000", "AffiliationID": "60033316", "AffiliationName": "Department of Physics and Astronomy, University of Gent"}, "55602709800": {"Name": "Vraeghe M.", "AuthorID": "55602709800", "AffiliationID": "60033316", "AffiliationName": "Department of Physics and Astronomy, University of Gent"}, "7004516842": {"Name": "Barwick S.W.", "AuthorID": "7004516842", "AffiliationID": "60007278", "AffiliationName": "Department of Physics and Astronomy, University of California"}, "6603930996": {"Name": "Yodh G.", "AuthorID": "6603930996", "AffiliationID": "60007278", "AffiliationName": "Department of Physics and Astronomy, University of California"}, "34879426200": {"Name": "Besson D.Z.", "AuthorID": "34879426200", "AffiliationID": "60015457", "AffiliationName": "Department of Physics and Astronomy, University of Kansas"}, "8935792000": {"Name": "Clark K.", "AuthorID": "8935792000", "AffiliationID": "108082101", "AffiliationName": "SNOLAB"}, "26421518100": {"Name": "Whitehorn N.", "AuthorID": "26421518100", "AffiliationID": "60027550", "AffiliationName": "Department of Physics and Astronomy, UCLA"}, "35425327000": {"Name": "Gallagher J.", "AuthorID": "35425327000", "AffiliationID": "60032179", "AffiliationName": "Department of Astronomy, University of Wisconsin"}, "57113242900": {"Name": "Bourbeau J.", "AuthorID": "57113242900", "AffiliationID": "60032179", "AffiliationName": "Department of Physics, Wisconsin IceCube Particle Astrophysics Center, University of Wisconsin"}, "55728545000": {"Name": "Braun J.", "AuthorID": "55728545000", "AffiliationID": "60032179", "AffiliationName": "Department of Physics, Wisconsin IceCube Particle Astrophysics Center, University of Wisconsin"}, "57201908896": {"Name": "Busse R.S.", "AuthorID": "57201908896", "AffiliationID": "60032179", "AffiliationName": "Department of Physics, Wisconsin IceCube Particle Astrophysics Center, University of Wisconsin"}, "35236462200": {"Name": "Chirkin D.", "AuthorID": "35236462200", "AffiliationID": "60032179", "AffiliationName": "Department of Physics, Wisconsin IceCube Particle Astrophysics Center, University of Wisconsin"}, "22996641400": {"Name": "Day M.", "AuthorID": "22996641400", "AffiliationID": "60032179", "AffiliationName": "Department of Physics, Wisconsin IceCube Particle Astrophysics Center, University of Wisconsin"}, "35236894900": {"Name": "Desiati P.", "AuthorID": "35236894900", "AffiliationID": "60032179", "AffiliationName": "Department of Physics, Wisconsin IceCube Particle Astrophysics Center, University of Wisconsin"}, "57203514047": {"Name": "D\u00edaz-V\u00e9lez J.C.", "AuthorID": "57203514047", "AffiliationID": "60032179", "AffiliationName": "Department of Physics, Wisconsin IceCube Particle Astrophysics Center, University of Wisconsin"}, "7005659377": {"Name": "Fahey S.", "AuthorID": "7005659377", "AffiliationID": "60032179", "AffiliationName": "Department of Physics, Wisconsin IceCube Particle Astrophysics Center, University of Wisconsin"}, "56715420800": {"Name": "Ghorbani K.", "AuthorID": "56715420800", "AffiliationID": "60032179", "AffiliationName": "Department of Physics, Wisconsin IceCube Particle Astrophysics Center, University of Wisconsin"}, "57110107600": {"Name": "Griffith Z.", "AuthorID": "57110107600", "AffiliationID": "60032179", "AffiliationName": "Department of Physics, Wisconsin IceCube Particle Astrophysics Center, University of Wisconsin"}, "16482562900": {"Name": "Halzen F.", "AuthorID": "16482562900", "AffiliationID": "60032179", "AffiliationName": "Department of Physics, Wisconsin IceCube Particle Astrophysics Center, University of Wisconsin"}, "7202629894": {"Name": "Hanson K.", "AuthorID": "7202629894", "AffiliationID": "60032179", "AffiliationName": "Department of Physics, Wisconsin IceCube Particle Astrophysics Center, University of Wisconsin"}, "57195684746": {"Name": "Hokanson-Fasig B.", "AuthorID": "57195684746", "AffiliationID": "60032179", "AffiliationName": "Department of Physics, Wisconsin IceCube Particle Astrophysics Center, University of Wisconsin"}, "35369749400": {"Name": "Hoshina K.", "AuthorID": "35369749400", "AffiliationID": "60025272", "AffiliationName": "Earthquake Research Institute, University of Tokyo"}, "57201900209": {"Name": "Hussain R.", "AuthorID": "57201900209", "AffiliationID": "60032179", "AffiliationName": "Department of Physics, Wisconsin IceCube Particle Astrophysics Center, University of Wisconsin"}, "55616856500": {"Name": "Jero K.", "AuthorID": "55616856500", "AffiliationID": "60032179", "AffiliationName": "Department of Physics, Wisconsin IceCube Particle Astrophysics Center, University of Wisconsin"}, "35237260500": {"Name": "Karle A.", "AuthorID": "35237260500", "AffiliationID": "60032179", "AffiliationName": "Department of Physics, Wisconsin IceCube Particle Astrophysics Center, University of Wisconsin"}, "55196156000": {"Name": "Kauer M.", "AuthorID": "55196156000", "AffiliationID": "60032179", "AffiliationName": "Department of Physics, Wisconsin IceCube Particle Astrophysics Center, University of Wisconsin"}, "35237115400": {"Name": "Kelley J.L.", "AuthorID": "35237115400", "AffiliationID": "60032179", "AffiliationName": "Department of Physics, Wisconsin IceCube Particle Astrophysics Center, University of Wisconsin"}, "55612510700": {"Name": "Kheirandish A.", "AuthorID": "55612510700", "AffiliationID": "60032179", "AffiliationName": "Department of Physics, Wisconsin IceCube Particle Astrophysics Center, University of Wisconsin"}, "57201897166": {"Name": "Leonard K.", "AuthorID": "57201897166", "AffiliationID": "60032179", "AffiliationName": "Department of Physics, Wisconsin IceCube Particle Astrophysics Center, University of Wisconsin"}, "57195679378": {"Name": "Liu Q.R.", "AuthorID": "57195679378", "AffiliationID": "60032179", "AffiliationName": "Department of Physics, Wisconsin IceCube Particle Astrophysics Center, University of Wisconsin"}, "57195676200": {"Name": "Luszczak W.", "AuthorID": "57195676200", "AffiliationID": "60032179", "AffiliationName": "Department of Physics, Wisconsin IceCube Particle Astrophysics Center, University of Wisconsin"}, "57190009975": {"Name": "Mancina S.", "AuthorID": "57190009975", "AffiliationID": "60032179", "AffiliationName": "Department of Physics, Wisconsin IceCube Particle Astrophysics Center, University of Wisconsin"}, "15819634200": {"Name": "Merino G.", "AuthorID": "15819634200", "AffiliationID": "60032179", "AffiliationName": "Department of Physics, Wisconsin IceCube Particle Astrophysics Center, University of Wisconsin"}, "57204103393": {"Name": "Pizzuto A.", "AuthorID": "57204103393", "AffiliationID": "60032179", "AffiliationName": "Department of Physics, Wisconsin IceCube Particle Astrophysics Center, University of Wisconsin"}, "57201897558": {"Name": "Safa I.", "AuthorID": "57201897558", "AffiliationID": "60032179", "AffiliationName": "Department of Physics, Wisconsin IceCube Particle Astrophysics Center, University of Wisconsin"}, "7402384757": {"Name": "Schneider A.", "AuthorID": "7402384757", "AffiliationID": "60032179", "AffiliationName": "Department of Physics, Wisconsin IceCube Particle Astrophysics Center, University of Wisconsin"}, "35244063900": {"Name": "Tobin M.N.", "AuthorID": "35244063900", "AffiliationID": "60032179", "AffiliationName": "Department of Physics, Wisconsin IceCube Particle Astrophysics Center, University of Wisconsin"}, "17342936700": {"Name": "Tosi D.", "AuthorID": "17342936700", "AffiliationID": "60032179", "AffiliationName": "Department of Physics, Wisconsin IceCube Particle Astrophysics Center, University of Wisconsin"}, "56623133200": {"Name": "Ty B.", "AuthorID": "56623133200", "AffiliationID": "60032179", "AffiliationName": "Department of Physics, Wisconsin IceCube Particle Astrophysics Center, University of Wisconsin"}, "26421460900": {"Name": "Vandenbroucke J.", "AuthorID": "26421460900", "AffiliationID": "60032179", "AffiliationName": "Department of Physics, Wisconsin IceCube Particle Astrophysics Center, University of Wisconsin"}, "36495970700": {"Name": "Van Eijk D.", "AuthorID": "36495970700", "AffiliationID": "60032179", "AffiliationName": "Department of Physics, Wisconsin IceCube Particle Astrophysics Center, University of Wisconsin"}, "49962721300": {"Name": "Wandkowsky N.", "AuthorID": "49962721300", "AffiliationID": "60032179", "AffiliationName": "Department of Physics, Wisconsin IceCube Particle Astrophysics Center, University of Wisconsin"}, "35838450200": {"Name": "Wendt C.", "AuthorID": "35838450200", "AffiliationID": "60032179", "AffiliationName": "Department of Physics, Wisconsin IceCube Particle Astrophysics Center, University of Wisconsin"}, "57198510870": {"Name": "Werthebach J.", "AuthorID": "57198510870", "AffiliationID": "60032179", "AffiliationName": "Department of Physics, Wisconsin IceCube Particle Astrophysics Center, University of Wisconsin"}, "6603965367": {"Name": "Westerhoff S.", "AuthorID": "6603965367", "AffiliationID": "60032179", "AffiliationName": "Department of Physics, Wisconsin IceCube Particle Astrophysics Center, University of Wisconsin"}, "56715282400": {"Name": "Wille L.", "AuthorID": "56715282400", "AffiliationID": "60032179", "AffiliationName": "Department of Physics, Wisconsin IceCube Particle Astrophysics Center, University of Wisconsin"}, "22936048700": {"Name": "Wood J.", "AuthorID": "22936048700", "AffiliationID": "60032179", "AffiliationName": "Department of Physics, Wisconsin IceCube Particle Astrophysics Center, University of Wisconsin"}, "57204113451": {"Name": "Xu D.L.", "AuthorID": "57204113451", "AffiliationID": "60032179", "AffiliationName": "Department of Physics, Wisconsin IceCube Particle Astrophysics Center, University of Wisconsin"}, "55049866900": {"Name": "Yuan T.", "AuthorID": "55049866900", "AffiliationID": "60032179", "AffiliationName": "Department of Physics, Wisconsin IceCube Particle Astrophysics Center, University of Wisconsin"}, "57218358689": {"Name": "Baum V.", "AuthorID": "57218358689", "AffiliationID": "60031216", "AffiliationName": "Institute of Physics, University of Mainz"}, "10139717100": {"Name": "B\u00f6ser S.", "AuthorID": "10139717100", "AffiliationID": "60031216", "AffiliationName": "Institute of Physics, University of Mainz"}, "57070156700": {"Name": "Di Lorenzo V.", "AuthorID": "57070156700", "AffiliationID": "60031216", "AffiliationName": "Institute of Physics, University of Mainz"}, "55934755700": {"Name": "Eberhardt B.", "AuthorID": "55934755700", "AffiliationID": "60031216", "AffiliationName": "Institute of Physics, University of Mainz"}, "56652060800": {"Name": "Ehrhardt T.", "AuthorID": "56652060800", "AffiliationID": "60031216", "AffiliationName": "Institute of Physics, University of Mainz"}, "57207721921": {"Name": "Fritz A.", "AuthorID": "57207721921", "AffiliationID": "60031216", "AffiliationName": "Institute of Physics, University of Mainz"}, "57201903203": {"Name": "Kappesser D.", "AuthorID": "57201903203", "AffiliationID": "60031216", "AffiliationName": "Institute of Physics, University of Mainz"}, "24755802900": {"Name": "K\u00f6pke L.", "AuthorID": "24755802900", "AffiliationID": "60031216", "AffiliationName": "Institute of Physics, University of Mainz"}, "57110384500": {"Name": "Kr\u00fcckl G.", "AuthorID": "57110384500", "AffiliationID": "60031216", "AffiliationName": "Institute of Physics, University of Mainz"}, "57204114682": {"Name": "Lohfink E.", "AuthorID": "57204114682", "AffiliationID": "60031216", "AffiliationName": "Institute of Physics, University of Mainz"}, "57194796635": {"Name": "Moment\u00e9 G.", "AuthorID": "57194796635", "AffiliationID": "60031216", "AffiliationName": "Institute of Physics, University of Mainz"}, "22136077600": {"Name": "Peiffer P.", "AuthorID": "22136077600", "AffiliationID": "60031216", "AffiliationName": "Institute of Physics, University of Mainz"}, "56418703400": {"Name": "Sandroos J.", "AuthorID": "56418703400", "AffiliationID": "60031216", "AffiliationName": "Institute of Physics, University of Mainz"}, "57110091300": {"Name": "Steuer A.", "AuthorID": "57110091300", "AffiliationID": "60031216", "AffiliationName": "Institute of Physics, University of Mainz"}, "35290777000": {"Name": "Wiebe K.", "AuthorID": "35290777000", "AffiliationID": "60031216", "AffiliationName": "Institute of Physics, University of Mainz"}, "35236487100": {"Name": "Andeen K.", "AuthorID": "35236487100", "AffiliationID": "60015720", "AffiliationName": "Department of Physics, Marquette University"}, "57209042614": {"Name": "Plum M.", "AuthorID": "57209042614", "AffiliationID": "60015720", "AffiliationName": "Department of Physics, Marquette University"}, "57192384142": {"Name": "Glauch T.", "AuthorID": "57192384142", "AffiliationID": "60019722", "AffiliationName": "Physik-department, Technische Universit\u00e4t M\u00fcnchen"}, "57210457547": {"Name": "Huber M.", "AuthorID": "57210457547", "AffiliationID": "60019722", "AffiliationName": "Physik-department, Technische Universit\u00e4t M\u00fcnchen"}, "55792416900": {"Name": "Krings K.", "AuthorID": "55792416900", "AffiliationID": "60019722", "AffiliationName": "Physik-department, Technische Universit\u00e4t M\u00fcnchen"}, "57198500001": {"Name": "Rea I.C.", "AuthorID": "57198500001", "AffiliationID": "60019722", "AffiliationName": "Physik-department, Technische Universit\u00e4t M\u00fcnchen"}, "6602123609": {"Name": "Resconi E.", "AuthorID": "6602123609", "AffiliationID": "60019722", "AffiliationName": "Physik-department, Technische Universit\u00e4t M\u00fcnchen"}, "56928403000": {"Name": "Turcati A.", "AuthorID": "56928403000", "AffiliationID": "60019722", "AffiliationName": "Physik-department, Technische Universit\u00e4t M\u00fcnchen"}, "57218361420": {"Name": "Wolf M.", "AuthorID": "57218361420", "AffiliationID": "60019722", "AffiliationName": "Physik-department, Technische Universit\u00e4t M\u00fcnchen"}, "36808939600": {"Name": "Classen L.", "AuthorID": "36808939600", "AffiliationID": "60000401", "AffiliationName": "Institut f\u00fcr Kernphysik, Westf\u00e4lische Wilhelms-Universit\u00e4t M\u00fcnster"}, "36066209200": {"Name": "Kappes A.", "AuthorID": "36066209200", "AffiliationID": "60000401", "AffiliationName": "Institut f\u00fcr Kernphysik, Westf\u00e4lische Wilhelms-Universit\u00e4t M\u00fcnster"}, "57204108271": {"Name": "Lozano Mariscal C.J.", "AuthorID": "57204108271", "AffiliationID": "60000401", "AffiliationName": "Institut f\u00fcr Kernphysik, Westf\u00e4lische Wilhelms-Universit\u00e4t M\u00fcnster"}, "35277064500": {"Name": "Dembinski H.", "AuthorID": "35277064500", "AffiliationID": "60000546, 60023004", "AffiliationName": "Bartol Research Institute, Department of Physics and Astronomy, University of Delaware"}, "35376407700": {"Name": "Evenson P.A.", "AuthorID": "35376407700", "AffiliationID": "60000546, 60023004", "AffiliationName": "Bartol Research Institute, Department of Physics and Astronomy, University of Delaware"}, "7004629004": {"Name": "Gaisser T.K.", "AuthorID": "7004629004", "AffiliationID": "60000546, 60023004", "AffiliationName": "Bartol Research Institute, Department of Physics and Astronomy, University of Delaware"}, "57193783591": {"Name": "Gonzalez J.G.", "AuthorID": "57193783591", "AffiliationID": "60000546, 60023004", "AffiliationName": "Bartol Research Institute, Department of Physics and Astronomy, University of Delaware"}, "56928127800": {"Name": "Koirala R.", "AuthorID": "56928127800", "AffiliationID": "60000546, 60023004", "AffiliationName": "Bartol Research Institute, Department of Physics and Astronomy, University of Delaware"}, "56927975500": {"Name": "Pandya H.", "AuthorID": "56927975500", "AffiliationID": "60000546, 60023004", "AffiliationName": "Bartol Research Institute, Department of Physics and Astronomy, University of Delaware"}, "6604049165": {"Name": "Seckel D.", "AuthorID": "6604049165", "AffiliationID": "60000546, 60023004", "AffiliationName": "Bartol Research Institute, Department of Physics and Astronomy, University of Delaware"}, "55517036200": {"Name": "Soldin D.", "AuthorID": "55517036200", "AffiliationID": "60000546, 60023004", "AffiliationName": "Bartol Research Institute, Department of Physics and Astronomy, University of Delaware"}, "7003289192": {"Name": "Stanev T.", "AuthorID": "7003289192", "AffiliationID": "60000546, 60023004", "AffiliationName": "Bartol Research Institute, Department of Physics and Astronomy, University of Delaware"}, "35228139700": {"Name": "Tilav S.", "AuthorID": "35228139700", "AffiliationID": "60000546, 60023004", "AffiliationName": "Bartol Research Institute, Department of Physics and Astronomy, University of Delaware"}, "9334469000": {"Name": "Maruyama R.", "AuthorID": "9334469000", "AffiliationID": "60005455", "AffiliationName": "Department of Physics, Yale University"}, "14121611000": {"Name": "Kurahashi N.", "AuthorID": "14121611000", "AffiliationID": "60014662", "AffiliationName": "Department of Physics, Drexel University"}, "57191750160": {"Name": "Relethford B.", "AuthorID": "57191750160", "AffiliationID": "60014662", "AffiliationName": "Department of Physics, Drexel University"}, "54927660400": {"Name": "Richman M.", "AuthorID": "54927660400", "AffiliationID": "60014662", "AffiliationName": "Department of Physics, Drexel University"}, "57201915695": {"Name": "Sclafani S.", "AuthorID": "57201915695", "AffiliationID": "60014662", "AffiliationName": "Department of Physics, Drexel University"}, "57188642133": {"Name": "Wills L.", "AuthorID": "57188642133", "AffiliationID": "60014662", "AffiliationName": "Department of Physics, Drexel University"}, "7201893408": {"Name": "Bai X.", "AuthorID": "7201893408", "AffiliationID": "60018394", "AffiliationName": "Physics Department, South Dakota School of Mines and Technology"}, "56275276900": {"Name": "Dvorak E.", "AuthorID": "56275276900", "AffiliationID": "60018394", "AffiliationName": "Physics Department, South Dakota School of Mines and Technology"}, "35372915400": {"Name": "Madsen J.", "AuthorID": "35372915400", "AffiliationID": "60031316", "AffiliationName": "Department of Physics, University of Wisconsin"}, "55032061900": {"Name": "Seunarine S.", "AuthorID": "55032061900", "AffiliationID": "60031316", "AffiliationName": "Department of Physics, University of Wisconsin"}, "35238925400": {"Name": "Spiczak G.M.", "AuthorID": "35238925400", "AffiliationID": "60031316", "AffiliationName": "Department of Physics, University of Wisconsin"}, "35277039200": {"Name": "Benzvi S.", "AuthorID": "35277039200", "AffiliationID": "60027165", "AffiliationName": "Department of Physics and Astronomy, University of Rochester"}, "57196628704": {"Name": "Cross R.", "AuthorID": "57196628704", "AffiliationID": "60027165", "AffiliationName": "Department of Physics and Astronomy, University of Rochester"}, "56417407200": {"Name": "Ahrens M.", "AuthorID": "56417407200", "AffiliationID": "60028378", "AffiliationName": "Oskar Klein Centre, Department of Physics, Stockholm University"}, "7101750622": {"Name": "Bohm C.", "AuthorID": "7101750622", "AffiliationID": "60028378", "AffiliationName": "Oskar Klein Centre, Department of Physics, Stockholm University"}, "57204106560": {"Name": "Deoskar K.", "AuthorID": "57204106560", "AffiliationID": "60028378", "AffiliationName": "Oskar Klein Centre, Department of Physics, Stockholm University"}, "56670440400": {"Name": "Dumm J.P.", "AuthorID": "56670440400", "AffiliationID": "60028378", "AffiliationName": "Oskar Klein Centre, Department of Physics, Stockholm University"}, "8630673800": {"Name": "Finley C.", "AuthorID": "8630673800", "AffiliationID": "60028378", "AffiliationName": "Oskar Klein Centre, Department of Physics, Stockholm University"}, "55055155500": {"Name": "Flis S.", "AuthorID": "55055155500", "AffiliationID": "60028378", "AffiliationName": "Oskar Klein Centre, Department of Physics, Stockholm University"}, "7004366250": {"Name": "Hultqvist K.", "AuthorID": "7004366250", "AffiliationID": "60028378", "AffiliationName": "Oskar Klein Centre, Department of Physics, Stockholm University"}, "57200707397": {"Name": "O'Sullivan E.", "AuthorID": "57200707397", "AffiliationID": "60028378", "AffiliationName": "Oskar Klein Centre, Department of Physics, Stockholm University"}, "8086257800": {"Name": "Walck C.", "AuthorID": "8086257800", "AffiliationID": "60028378", "AffiliationName": "Oskar Klein Centre, Department of Physics, Stockholm University"}, "35227482800": {"Name": "Kiryluk J.", "AuthorID": "35227482800", "AffiliationID": "60026415", "AffiliationName": "Department of Physics and Astronomy, Stony Brook University"}, "55615837800": {"Name": "Niederhausen H.", "AuthorID": "55615837800", "AffiliationID": "60026415", "AffiliationName": "Department of Physics and Astronomy, Stony Brook University"}, "57198773651": {"Name": "Xu Y.", "AuthorID": "57198773651", "AffiliationID": "60026415", "AffiliationName": "Department of Physics and Astronomy, Stony Brook University"}, "55767960600": {"Name": "Dujmovic H.", "AuthorID": "55767960600", "AffiliationID": "60007511", "AffiliationName": "Department of Physics, Sungkyunkwan University"}, "56712452100": {"Name": "In S.", "AuthorID": "56712452100", "AffiliationID": "60007511", "AffiliationName": "Department of Physics, Sungkyunkwan University"}, "57109815100": {"Name": "Jeong M.", "AuthorID": "57109815100", "AffiliationID": "60007511", "AffiliationName": "Department of Physics, Sungkyunkwan University"}, "57202839610": {"Name": "Kang W.", "AuthorID": "57202839610", "AffiliationID": "60007511", "AffiliationName": "Department of Physics, Sungkyunkwan University"}, "55854181300": {"Name": "Kim J.", "AuthorID": "55854181300", "AffiliationID": "60007511", "AffiliationName": "Department of Physics, Sungkyunkwan University"}, "35227850400": {"Name": "Rott C.", "AuthorID": "35227850400", "AffiliationID": "60007511", "AffiliationName": "Department of Physics, Sungkyunkwan University"}, "56437722000": {"Name": "T\u00f6nnis C.", "AuthorID": "56437722000", "AffiliationID": "60007511", "AffiliationName": "Department of Physics, Sungkyunkwan University"}, "43761985400": {"Name": "Kopper S.", "AuthorID": "43761985400", "AffiliationID": "60025371", "AffiliationName": "Department of Physics and Astronomy, University of Alabama"}, "57195681496": {"Name": "Nakarmi P.", "AuthorID": "57195681496", "AffiliationID": "60025371", "AffiliationName": "Department of Physics and Astronomy, University of Alabama"}, "7102974462": {"Name": "Pepper J.A.", "AuthorID": "7102974462", "AffiliationID": "60025371", "AffiliationName": "Department of Physics and Astronomy, University of Alabama"}, "35277451800": {"Name": "Santander M.", "AuthorID": "35277451800", "AffiliationID": "60025371", "AffiliationName": "Department of Physics and Astronomy, University of Alabama"}, "35228109900": {"Name": "Toale P.A.", "AuthorID": "35228109900", "AffiliationID": "60025371", "AffiliationName": "Department of Physics and Astronomy, University of Alabama"}, "57213469051": {"Name": "Williams D.R.", "AuthorID": "57213469051", "AffiliationID": "60025371", "AffiliationName": "Department of Physics and Astronomy, University of Alabama"}, "7102333279": {"Name": "Cowen D.F.", "AuthorID": "7102333279", "AffiliationID": "60001439", "AffiliationName": "Department of Physics, Pennsylvania State University"}, "57192828127": {"Name": "Anderson T.", "AuthorID": "57192828127", "AffiliationID": "60001439", "AffiliationName": "Department of Physics, Pennsylvania State University"}, "55898828900": {"Name": "Delaunay J.J.", "AuthorID": "55898828900", "AffiliationID": "60001439", "AffiliationName": "Department of Physics, Pennsylvania State University"}, "54419932600": {"Name": "Dunkman M.", "AuthorID": "54419932600", "AffiliationID": "60001439", "AffiliationName": "Department of Physics, Pennsylvania State University"}, "54414191100": {"Name": "Eller P.", "AuthorID": "54414191100", "AffiliationID": "60001439", "AffiliationName": "Department of Physics, Pennsylvania State University"}, "55238921700": {"Name": "Huang F.", "AuthorID": "55238921700", "AffiliationID": "60001439", "AffiliationName": "Department of Physics, Pennsylvania State University"}, "35519765300": {"Name": "Keivani A.", "AuthorID": "35519765300", "AffiliationID": "60001439", "AffiliationName": "Department of Physics, Pennsylvania State University"}, "56638009400": {"Name": "Lanfranchi J.L.", "AuthorID": "56638009400", "AffiliationID": "60001439", "AffiliationName": "Department of Physics, Pennsylvania State University"}, "55606303200": {"Name": "Pankova D.V.", "AuthorID": "55606303200", "AffiliationID": "60001439", "AffiliationName": "Department of Physics, Pennsylvania State University"}, "57192068717": {"Name": "Turley C.F.", "AuthorID": "57192068717", "AffiliationID": "60001439", "AffiliationName": "Department of Physics, Pennsylvania State University"}, "57191755031": {"Name": "Weiss M.J.", "AuthorID": "57191755031", "AffiliationID": "60001439", "AffiliationName": "Department of Physics, Pennsylvania State University"}, "35184751400": {"Name": "Botner O.", "AuthorID": "35184751400", "AffiliationID": "60003858", "AffiliationName": "Department of Physics and Astronomy, Uppsala University"}, "57190009248": {"Name": "Burgman A.", "AuthorID": "57190009248", "AffiliationID": "60003858", "AffiliationName": "Department of Physics and Astronomy, Uppsala University"}, "8771784700": {"Name": "Hallgren A.", "AuthorID": "8771784700", "AffiliationID": "60003858", "AffiliationName": "Department of Physics and Astronomy, Uppsala University"}, "35277417600": {"Name": "P\u00e9rez De Los Heros C.", "AuthorID": "35277417600", "AffiliationID": "60003858", "AffiliationName": "Department of Physics and Astronomy, Uppsala University"}, "55869046400": {"Name": "Unger E.", "AuthorID": "55869046400", "AffiliationID": "60003858", "AffiliationName": "Department of Physics and Astronomy, Uppsala University"}, "7401802922": {"Name": "Becker K.H.", "AuthorID": "7401802922", "AffiliationID": "60022995", "AffiliationName": "Department of Physics, University of Wuppertal"}, "43762032700": {"Name": "Bindig D.", "AuthorID": "43762032700", "AffiliationID": "60022995", "AffiliationName": "Department of Physics, University of Wuppertal"}, "56186878600": {"Name": "Helbing K.", "AuthorID": "56186878600", "AffiliationID": "60022995", "AffiliationName": "Department of Physics, University of Wuppertal"}, "35237220700": {"Name": "Hickford S.", "AuthorID": "35237220700", "AffiliationID": "60022995", "AffiliationName": "Department of Physics, University of Wuppertal"}, "55350099700": {"Name": "Hoffmann R.", "AuthorID": "55350099700", "AffiliationID": "60022995", "AffiliationName": "Department of Physics, University of Wuppertal"}, "57191756134": {"Name": "Lauber F.", "AuthorID": "57191756134", "AffiliationID": "60022995", "AffiliationName": "Department of Physics, University of Wuppertal"}, "35786580700": {"Name": "Naumann U.", "AuthorID": "35786580700", "AffiliationID": "60022995", "AffiliationName": "Department of Physics, University of Wuppertal"}, "57110370700": {"Name": "Obertacke Pollmann A.", "AuthorID": "57110370700", "AffiliationID": "60022995", "AffiliationName": "Department of Physics, University of Wuppertal"}, "57203580983": {"Name": "Ackermann M.", "AuthorID": "57203580983", "AffiliationID": "60030635", "AffiliationName": "DESY"}, "57188547921": {"Name": "Bernardini E.", "AuthorID": "57188547921", "AffiliationID": "60030635", "AffiliationName": "DESY"}, "57190010995": {"Name": "Blot S.", "AuthorID": "57190010995", "AffiliationID": "60030635", "AffiliationName": "DESY"}, "57195314289": {"Name": "Bradascio F.", "AuthorID": "57195314289", "AffiliationID": "60030635", "AffiliationName": "DESY"}, "55317506000": {"Name": "Bretz H.P.", "AuthorID": "55317506000", "AffiliationID": "60030635", "AffiliationName": "DESY"}, "57189362095": {"Name": "Brostean-Kaiser J.", "AuthorID": "57189362095", "AffiliationID": "60030635", "AffiliationName": "DESY"}, "35236759000": {"Name": "Franckowiak A.", "AuthorID": "35236759000", "AffiliationID": "60030635", "AffiliationName": "DESY"}, "55033666700": {"Name": "Jacobi E.", "AuthorID": "55033666700", "AffiliationID": "60030635", "AffiliationName": "DESY"}, "55935231500": {"Name": "Karg T.", "AuthorID": "55935231500", "AffiliationID": "60030635", "AffiliationName": "DESY"}, "57189366447": {"Name": "Kintscher T.", "AuthorID": "57189366447", "AffiliationID": "60030635", "AffiliationName": "DESY"}, "53865219900": {"Name": "Kunwar S.", "AuthorID": "53865219900", "AffiliationID": "60030635", "AffiliationName": "DESY"}, "6701839327": {"Name": "Nahnhauer R.", "AuthorID": "6701839327", "AffiliationID": "60030635", "AffiliationName": "DESY"}, "56816691100": {"Name": "Rauch L.", "AuthorID": "56816691100", "AffiliationID": "60030635", "AffiliationName": "DESY"}, "57192372339": {"Name": "Satalecka K.", "AuthorID": "57192372339", "AffiliationID": "60030635", "AffiliationName": "DESY"}, "7004012076": {"Name": "Spiering C.", "AuthorID": "7004012076", "AffiliationID": "60030635", "AffiliationName": "DESY"}, "57218185647": {"Name": "Stachurska J.", "AuthorID": "57218185647", "AffiliationID": "60030635", "AffiliationName": "DESY"}, "55516802700": {"Name": "Stasik A.", "AuthorID": "55516802700", "AffiliationID": "60030635", "AffiliationName": "DESY"}, "57207153999": {"Name": "Stein R.", "AuthorID": "57207153999", "AffiliationID": "60030635", "AffiliationName": "DESY"}, "56086304100": {"Name": "Strotjohann N.L.", "AuthorID": "56086304100", "AffiliationID": "60030635", "AffiliationName": "DESY"}, "56418502500": {"Name": "Terliuk A.", "AuthorID": "56418502500", "AffiliationID": "60030635", "AffiliationName": "DESY"}, "55516813700": {"Name": "Usner M.", "AuthorID": "55516813700", "AffiliationID": "60030635", "AffiliationName": "DESY"}, "35291128700": {"Name": "Van Santen J.", "AuthorID": "35291128700", "AffiliationID": "60030635", "AffiliationName": "DESY"}, "null": {"Name": null, "AuthorID": null, "AffiliationID": null, "AffiliationName": null}}}