{"Title": "Multiple drivers of decline in the global status of freshwater crayfish (Decapoda: Astacidea)", "Year": 2015, "Source": "Philos. Trans. R. Soc. B Biol. Sci.", "Volume": "370", "Issue": 1662, "Art.No": null, "PageStart": 1, "PageEnd": 11, "CitedBy": 115, "DOI": "10.1098/rstb.2014.0060", "Link": "https://www.scopus.com/inward/record.uri?partnerID=HzOxMe3b&scp=84964695240&origin=inward", "Abstract": "\u00a9 2015 The Author(s) Published by the Royal Society. All rights reserved.Rates of biodiversity loss are higher in freshwater ecosystems than in most terrestrial or marine ecosystems, making freshwater conservation a priority. However, prioritization methods are impeded by insufficient knowledge on the distribution and conservation status of freshwater taxa, particularly invertebrates. We evaluated the extinction risk of the world\u2019s 590 freshwater crayfish species using the IUCN Categories and Criteria and found 32% of all species are threatened with extinction. The level of extinction risk differed between families, with proportionally more threatened species in the Parastacidae and Astacidae than in the Cambaridae. Four described species were Extinct and 21% were assessed as Data Deficient. There was geographical variation in the dominant threats affecting the main centres of crayfish diversity. The majority of threatened US and Mexican species face threats associated with urban development, pollution, damming and water management. Conversely, the majority of Australian threatened species are affected by climate change, harvesting, agriculture and invasive species. Only a small proportion of crayfish are found within the boundaries of protected areas, suggesting that alternative means of long-term protection will be required. Our study highlights many of the significant challenges yet to come for freshwater biodiversity unless conservation planning shifts from a reactive to proactive approach.", "AuthorKeywords": ["Crayfish", "Extinction risk", "Freshwater biodiversity", "IUCN red list", "Threatened"], "IndexKeywords": ["Animal Distribution", "Animals", "Astacoidea", "Australia", "Conservation of Natural Resources", "Endangered Species", "Fresh Water", "Geography", "Population Dynamics", "Species Specificity"], "DocumentType": "Journal", "PublicationStage": null, "OpenAccess": 1, "EID": "2-s2.0-84964695240", "SubjectAreas": [["Biochemistry, Genetics and Molecular Biology (all)", "BIOC", "1300"], ["Agricultural and Biological Sciences (all)", "AGRI", "1100"]], "AuthorData": {"37026947600": {"Name": "Richman N.I.", "AuthorID": "37026947600", "AffiliationID": "60025779", "AffiliationName": "School of Environment, Natural Resources and Geography, Bangor University"}, "12446161700": {"Name": "B\u00f6hm M.", "AuthorID": "12446161700", "AffiliationID": "60005453, 60009498", "AffiliationName": "Institute of Zoology, Zoological Society of London"}, "55388537800": {"Name": "Jones J.P.G.", "AuthorID": "55388537800", "AffiliationID": "60025779", "AffiliationName": "School of Environment, Natural Resources and Geography, Bangor University"}, "56248250700": {"Name": "Adams S.B.", "AuthorID": "56248250700", "AffiliationID": "60023249, 60003342", "AffiliationName": "USDA Forest Service, Southern Research Station, Center for Bottomland Hardwoods Research"}, "7201967544": {"Name": "Alvarez F.", "AuthorID": "7201967544", "AffiliationID": "60032442", "AffiliationName": "Colecci\u00f3n Nacional de Crust\u00e1ceos, Instituto de Biolog\u03afa, Universidad Nacional Aut\u00f3noma de M\u00e9xico"}, "7003864609": {"Name": "Bergey E.A.", "AuthorID": "7003864609", "AffiliationID": "60030931", "AffiliationName": "Oklahoma Biological Survey and Department of Biology, University of Oklahoma"}, "36083886900": {"Name": "Bunn J.J.S.", "AuthorID": "36083886900", "AffiliationID": "60105210", "AffiliationName": "School of Natural Sciences, Edith Cowan University"}, "55668106900": {"Name": "Burnham Q.", "AuthorID": "55668106900", "AffiliationID": "60105210", "AffiliationName": "School of Natural Sciences, Edith Cowan University"}, "14027848800": {"Name": "Coughran J.", "AuthorID": "14027848800", "AffiliationID": "114889260", "AffiliationName": "Jagabar Environmental"}, "7004554022": {"Name": "Horwitz P.", "AuthorID": "7004554022", "AffiliationID": "60105210", "AffiliationName": "School of Natural Sciences, Edith Cowan University"}, "21933753300": {"Name": "Cordeiro J.", "AuthorID": "21933753300", "AffiliationID": "114889534", "AffiliationName": "Northeast Natural History and Supply"}, "7006440923": {"Name": "Crandall K.A.", "AuthorID": "7006440923", "AffiliationID": "60007670, 60015033", "AffiliationName": "Department of Invertebrate Zoology, National Museum of Natural History, Smithsonian Institution"}, "36508585200": {"Name": "Dawkins K.L.", "AuthorID": "36508585200", "AffiliationID": "60032987", "AffiliationName": "Australian Rivers Institute, Griffith School of Environment, Griffith University"}, "6701713017": {"Name": "Distefano R.J.", "AuthorID": "6701713017", "AffiliationID": "60024303", "AffiliationName": "Missouri Department of Conservation"}, "7006078543": {"Name": "Doran N.E.", "AuthorID": "7006078543", "AffiliationID": "60015356", "AffiliationName": "Bookend Trust and the School of Biological Sciences, University of Tasmania"}, "10043414100": {"Name": "Edsman L.", "AuthorID": "10043414100", "AffiliationID": "60027152, 60002540", "AffiliationName": "Institute of Freshwater Research, Department of Aquatic Resources, Swedish University of Agricultural Sciences"}, "6701688556": {"Name": "Eversole A.G.", "AuthorID": "6701688556", "AffiliationID": "60026610", "AffiliationName": "School of Agricultural, Forestry and Environmental Sciences, Clemson University"}, "6602326035": {"Name": "F\u00fcreder L.", "AuthorID": "6602326035", "AffiliationID": "60009999", "AffiliationName": "River Ecology and Conservation, Institute of Ecology, University of Innsbruck"}, "36084349100": {"Name": "Furse J.M.", "AuthorID": "36084349100", "AffiliationID": "60032987", "AffiliationName": "Griffith School of Environment and the Environmental Futures Research Institute, Griffith University, Gold Coast Campus"}, "7005731313": {"Name": "Gherardi F.", "AuthorID": "7005731313", "AffiliationID": "60021859", "AffiliationName": "Dipartimento di Biologia, Universit\u00e0 degli Studi di Firenze"}, "6603407633": {"Name": "Hamr P.", "AuthorID": "6603407633", "AffiliationID": "100513165", "AffiliationName": "Upper Canada College"}, "6701567252": {"Name": "Holdich D.M.", "AuthorID": "6701567252", "AffiliationID": "114889653", "AffiliationName": "Crayfish Survey and Research, Peak Ecology Limited, Arden House"}, "8233962300": {"Name": "Johnston K.", "AuthorID": "8233962300", "AffiliationID": "60019939", "AffiliationName": "Marine and Freshwater Research Laboratory, Murdoch University"}, "7408262824": {"Name": "Jones C.M.", "AuthorID": "7408262824", "AffiliationID": "60019870", "AffiliationName": "James Cook University, School of Marine and Tropical Biology"}, "7501548413": {"Name": "Jones R.L.", "AuthorID": "7501548413", "AffiliationID": "60005274, 60024259", "AffiliationName": "Mississippi Department of Wildlife, Fisheries, and Parks, Museum of Natural Science"}, "55458411000": {"Name": "Jones T.G.", "AuthorID": "55458411000", "AffiliationID": "60005085", "AffiliationName": "Department of Integrated Science and Technology, Marshall University"}, "55256903500": {"Name": "Kawai T.", "AuthorID": "55256903500", "AffiliationID": "112757610", "AffiliationName": "Wakkanai Fisheries Institute"}, "7006782958": {"Name": "Lawler S.", "AuthorID": "7006782958", "AffiliationID": "60006925", "AffiliationName": "Department of Environmental Management and Ecology, La Trobe University"}, "56481601200": {"Name": "L\u00f3pez-Mej\u03afa M.", "AuthorID": "56481601200", "AffiliationID": "60013079", "AffiliationName": "Evolutionary Biology and Population Genetics Laboratory, Universidad de Quintana Roo, Unidad Acad\u00e9mica Cozumel"}, "14054650100": {"Name": "Miller R.M.", "AuthorID": "14054650100", "AffiliationID": "115902796", "AffiliationName": "International Union for Conservation of Nature"}, "36174131900": {"Name": "Pedraza-Lara C.", "AuthorID": "36174131900", "AffiliationID": "60011149", "AffiliationName": "Trinity College Dublin"}, "7402534285": {"Name": "Richardson A.M.M.", "AuthorID": "7402534285", "AffiliationID": "60015356", "AffiliationName": "School of Biology, University of Tasmania"}, "23096444700": {"Name": "Schultz M.B.", "AuthorID": "23096444700", "AffiliationID": "60026553", "AffiliationName": "Department of Biochemistry and Molecular Biology, University of Melbourne"}, "8534318500": {"Name": "Schuster G.A.", "AuthorID": "8534318500", "AffiliationID": null, "AffiliationName": null}, "56227975500": {"Name": "Sibley P.J.", "AuthorID": "56227975500", "AffiliationID": "60020560", "AffiliationName": "Environment Agency, Wessex Area, Rivers House, East Quay"}, "57202436426": {"Name": "Souty-Grosset C.", "AuthorID": "57202436426", "AffiliationID": "60032653, 60008134", "AffiliationName": "Laboratoire Ecologie et Biologie des Interactions, Universit\u00e9 de Poitiers, Equipe Ecologie Evolution Symbiose, UMR CNRS"}, "55574187464": {"Name": "Taylor C.A.", "AuthorID": "55574187464", "AffiliationID": "60007313, 60110549", "AffiliationName": "Prairie Research Institute, Illinois Natural History Survey"}, "8627743000": {"Name": "Thoma R.F.", "AuthorID": "8627743000", "AffiliationID": "115967264", "AffiliationName": "Midwest Biodiversity Institute"}, "14061375400": {"Name": "Walls J.", "AuthorID": "14061375400", "AffiliationID": "60026911", "AffiliationName": "Department of Biological Sciences, Louisiana State University Alexandria"}, "56481078500": {"Name": "Walsh T.S.", "AuthorID": "56481078500", "AffiliationID": null, "AffiliationName": null}, "24491824300": {"Name": "Collen B.", "AuthorID": "24491824300", "AffiliationID": "60022148", "AffiliationName": "Centre for Biodiversity and Environmental Research, University College London"}}}