{"Title": "Prevention of dementia by targeting risk factors", "Year": 2018, "Source": "Lancet", "Volume": "391", "Issue": 10130, "Art.No": null, "PageStart": 1575, "PageEnd": null, "CitedBy": 7, "DOI": "10.1016/S0140-6736(18)30579-8", "Link": "https://www.scopus.com/inward/record.uri?partnerID=HzOxMe3b&scp=85045584258&origin=inward", "Abstract": null, "AuthorKeywords": null, "IndexKeywords": ["Dementia", "Humans", "Risk Factors"], "DocumentType": "Journal", "PublicationStage": null, "OpenAccess": 1, "EID": "2-s2.0-85045584258", "SubjectAreas": [["Medicine (all)", "MEDI", "2700"]], "AuthorData": {"35557252600": {"Name": "Warren J.D.", "AuthorID": "35557252600", "AffiliationID": "60172674, 60024544", "AffiliationName": "UCL Hospitals National Institute for Health Research Biomedical Research Centre"}, "6701719104": {"Name": "Bamiou D.E.", "AuthorID": "6701719104", "AffiliationID": "60172674, 60024544", "AffiliationName": "UCL Hospitals National Institute for Health Research Biomedical Research Centre"}}}